{
  "fund_id": "M0146_2565",
  "symbol": "SCBRMPGF(A)",
  "fund_name": "SCB Platinum Global RMF",
  "amc": "SCB ASSET MANAGEMENT COMPANY LIMITED",
  "metadata": {
    "fund_classification": "-",
    "management_style": "AN",
    "dividend_policy": "No",
    "risk_level": 6,
    "fund_type": "RMF"
  },
  "latest_nav": {
    "nav_date": "2025-11-06",
    "last_val": 10.7445,
    "previous_val": 0,
    "net_asset": 57985524,
    "buy_price": 10.7445,
    "sell_price": 10.7446,
    "change": 10.7445,
    "change_percent": 0,
    "last_upd_date": "2025-11-11T08:11:44.25"
  },
  "nav_history_30d": [
    {
      "nav_date": "2025-09-25",
      "last_val": 10.5017,
      "previous_val": 0,
      "net_asset": 57575400,
      "buy_price": 10.5017,
      "sell_price": 10.5018
    },
    {
      "nav_date": "2025-09-26",
      "last_val": 10.5667,
      "previous_val": 0,
      "net_asset": 58031412,
      "buy_price": 10.5667,
      "sell_price": 10.5668
    },
    {
      "nav_date": "2025-09-29",
      "last_val": 10.4556,
      "previous_val": 0,
      "net_asset": 57435152,
      "buy_price": 10.4556,
      "sell_price": 10.4557
    },
    {
      "nav_date": "2025-09-30",
      "last_val": 10.4582,
      "previous_val": 0,
      "net_asset": 57469652,
      "buy_price": 10.4582,
      "sell_price": 10.4583
    },
    {
      "nav_date": "2025-10-01",
      "last_val": 10.5237,
      "previous_val": 0,
      "net_asset": 57887976,
      "buy_price": 0,
      "sell_price": 0
    },
    {
      "nav_date": "2025-10-02",
      "last_val": 10.5516,
      "previous_val": 0,
      "net_asset": 58041480,
      "buy_price": 10.5516,
      "sell_price": 10.5517
    },
    {
      "nav_date": "2025-10-03",
      "last_val": 10.5501,
      "previous_val": 0,
      "net_asset": 58036556,
      "buy_price": 0,
      "sell_price": 0
    },
    {
      "nav_date": "2025-10-06",
      "last_val": 10.573,
      "previous_val": 0,
      "net_asset": 58162816,
      "buy_price": 10.573,
      "sell_price": 10.5731
    },
    {
      "nav_date": "2025-10-07",
      "last_val": 10.5862,
      "previous_val": 0,
      "net_asset": 57890520,
      "buy_price": 0,
      "sell_price": 0
    },
    {
      "nav_date": "2025-10-08",
      "last_val": 10.5529,
      "previous_val": 0,
      "net_asset": 57708840,
      "buy_price": 10.5529,
      "sell_price": 10.553
    },
    {
      "nav_date": "2025-10-09",
      "last_val": 10.5836,
      "previous_val": 0,
      "net_asset": 57270328,
      "buy_price": 10.5836,
      "sell_price": 10.5837
    },
    {
      "nav_date": "2025-10-10",
      "last_val": 10.5176,
      "previous_val": 0,
      "net_asset": 56752228,
      "buy_price": 10.5176,
      "sell_price": 10.5177
    },
    {
      "nav_date": "2025-10-14",
      "last_val": 10.3673,
      "previous_val": 0,
      "net_asset": 55855424,
      "buy_price": 10.3673,
      "sell_price": 10.3674
    },
    {
      "nav_date": "2025-10-15",
      "last_val": 10.4888,
      "previous_val": 0,
      "net_asset": 56501376,
      "buy_price": 10.4888,
      "sell_price": 10.4889
    },
    {
      "nav_date": "2025-10-16",
      "last_val": 10.522,
      "previous_val": 0,
      "net_asset": 56704616,
      "buy_price": 10.522,
      "sell_price": 10.5221
    },
    {
      "nav_date": "2025-10-17",
      "last_val": 10.481,
      "previous_val": 0,
      "net_asset": 56428140,
      "buy_price": 10.481,
      "sell_price": 10.4811
    },
    {
      "nav_date": "2025-10-20",
      "last_val": 10.5805,
      "previous_val": 0,
      "net_asset": 57075352,
      "buy_price": 10.5805,
      "sell_price": 10.5806
    },
    {
      "nav_date": "2025-10-21",
      "last_val": 10.6295,
      "previous_val": 0,
      "net_asset": 57361664,
      "buy_price": 10.6295,
      "sell_price": 10.6296
    },
    {
      "nav_date": "2025-10-22",
      "last_val": 10.6811,
      "previous_val": 0,
      "net_asset": 57646080,
      "buy_price": 10.6811,
      "sell_price": 10.6812
    },
    {
      "nav_date": "2025-10-24",
      "last_val": 10.7027,
      "previous_val": 0,
      "net_asset": 57799544,
      "buy_price": 10.7027,
      "sell_price": 10.7028
    },
    {
      "nav_date": "2025-10-27",
      "last_val": 10.6917,
      "previous_val": 0,
      "net_asset": 57797576,
      "buy_price": 10.6917,
      "sell_price": 10.6918
    },
    {
      "nav_date": "2025-10-28",
      "last_val": 10.6523,
      "previous_val": 0,
      "net_asset": 57639112,
      "buy_price": 10.6523,
      "sell_price": 10.6524
    },
    {
      "nav_date": "2025-10-29",
      "last_val": 10.5893,
      "previous_val": 0,
      "net_asset": 57175852,
      "buy_price": 0,
      "sell_price": 0
    },
    {
      "nav_date": "2025-10-30",
      "last_val": 10.609,
      "previous_val": 0,
      "net_asset": 57281988,
      "buy_price": 10.609,
      "sell_price": 10.6091
    },
    {
      "nav_date": "2025-10-31",
      "last_val": 10.6058,
      "previous_val": 0,
      "net_asset": 57339972,
      "buy_price": 10.6058,
      "sell_price": 10.6059
    },
    {
      "nav_date": "2025-11-03",
      "last_val": 10.5585,
      "previous_val": 0,
      "net_asset": 57099820,
      "buy_price": 10.5585,
      "sell_price": 10.5586
    },
    {
      "nav_date": "2025-11-04",
      "last_val": 10.5797,
      "previous_val": 0,
      "net_asset": 57077572,
      "buy_price": 10.5797,
      "sell_price": 10.5798
    },
    {
      "nav_date": "2025-11-05",
      "last_val": 10.6163,
      "previous_val": 0,
      "net_asset": 57226568,
      "buy_price": 10.6163,
      "sell_price": 10.6164
    },
    {
      "nav_date": "2025-11-06",
      "last_val": 10.7445,
      "previous_val": 0,
      "net_asset": 57985524,
      "buy_price": 10.7445,
      "sell_price": 10.7446
    }
  ],
  "dividends": [],
  "performance": {
    "ytd": 5.45,
    "3m": 2.04,
    "6m": -2.31,
    "1y": 1.32,
    "3y": 6.46,
    "5y": null,
    "10y": null,
    "since_inception": 1.34
  },
  "benchmark": {
    "name": "Bloomberg Developed Markets Large & Mid Cap Net Return Index (EUR)",
    "returns": {
      "ytd": 4.16,
      "3m": 7.12,
      "6m": 10.43,
      "1y": 11.48,
      "3y": 15.42,
      "5y": null,
      "10y": null
    }
  },
  "risk_metrics": null,
  "asset_allocation": [
    {
      "asset_class": "หน่วยลงทุน",
      "percentage": 99.68
    },
    {
      "asset_class": "เงินฝาก",
      "percentage": 1.57
    },
    {
      "asset_class": "อื่น ๆ",
      "percentage": -0.14
    },
    {
      "asset_class": "ตราสารอนุพันธ์",
      "percentage": -1.11
    }
  ],
  "category": null,
  "fees": [
    {
      "fee_type": "Unknown",
      "fee_desc": "ค่าใช้จ่ายอื่นๆ",
      "fee_value": null,
      "fee_remark": null
    },
    {
      "fee_type": "Unknown",
      "fee_desc": "ค่าธรรมเนียมการขายหน่วยลงทุน (Front-end Fee)",
      "fee_value": null,
      "fee_remark": null
    },
    {
      "fee_type": "Unknown",
      "fee_desc": "ค่าธรรมเนียมการจัดการ",
      "fee_value": null,
      "fee_remark": null
    },
    {
      "fee_type": "Unknown",
      "fee_desc": "ค่าธรรมเนียมการรับซื้อคืนหน่วยลงทุน (Back-end Fee)",
      "fee_value": null,
      "fee_remark": null
    },
    {
      "fee_type": "Unknown",
      "fee_desc": "ค่าธรรมเนียมการสับเปลี่ยนหน่วยลงทุนเข้า (SWITCHING IN)",
      "fee_value": null,
      "fee_remark": null
    },
    {
      "fee_type": "Unknown",
      "fee_desc": "ค่าธรรมเนียมการสับเปลี่ยนหน่วยลงทุนออก (SWITCHING OUT)",
      "fee_value": null,
      "fee_remark": null
    },
    {
      "fee_type": "Unknown",
      "fee_desc": "ค่าธรรมเนียมการโอนหน่วยลงทุน",
      "fee_value": null,
      "fee_remark": null
    },
    {
      "fee_type": "Unknown",
      "fee_desc": "ค่าธรรมเนียมนายทะเบียนหน่วย",
      "fee_value": null,
      "fee_remark": null
    },
    {
      "fee_type": "Unknown",
      "fee_desc": "ค่าธรรมเนียมผู้ดูแลผลประโยชน์",
      "fee_value": null,
      "fee_remark": null
    },
    {
      "fee_type": "Unknown",
      "fee_desc": "ค่าธรรมเนียมและค่าใช้จ่ายรวมทั้งหมด",
      "fee_value": null,
      "fee_remark": null
    }
  ],
  "involved_parties": [
    {
      "party_role": "Unknown",
      "party_name": "Unknown"
    },
    {
      "party_role": "Unknown",
      "party_name": "Unknown"
    },
    {
      "party_role": "Unknown",
      "party_name": "Unknown"
    },
    {
      "party_role": "Unknown",
      "party_name": "Unknown"
    },
    {
      "party_role": "Unknown",
      "party_name": "Unknown"
    },
    {
      "party_role": "Unknown",
      "party_name": "Unknown"
    },
    {
      "party_role": "Unknown",
      "party_name": "Unknown"
    },
    {
      "party_role": "Unknown",
      "party_name": "Unknown"
    },
    {
      "party_role": "Unknown",
      "party_name": "Unknown"
    }
  ],
  "top_holdings": null,
  "risk_factors": [
    {
      "risk_type": "Unknown",
      "risk_desc": ""
    },
    {
      "risk_type": "Unknown",
      "risk_desc": ""
    },
    {
      "risk_type": "Unknown",
      "risk_desc": ""
    }
  ],
  "suitability": {
    "investment_horizon": null,
    "risk_level": "4Lil4LiH4LiX4Li44LiZ4LmD4LiZ4LiV4Lij4Liy4Liq4Liy4Lij4LiX4Li44LiZ4LmA4Lib4LmH4LiZ4Lir4Lil4Lix4LiBIOC5guC4lOC4ouC5gOC4ieC4peC4teC5iOC4ouC5g+C4meC4o+C4reC4muC4m+C4teC5hOC4oeC5iOC4meC5ieC4reC4ouC4geC4p+C5iOC4siA4MCUg4LiC4Lit4LiHIE5BVg==",
    "target_investor": null
  },
  "document_urls": {
    "factsheet_url": "https://secdocumentstorage.blob.core.windows.net/fundfactsheet/M0146_2565.pdf",
    "annual_report_url": "-",
    "halfyear_report_url": "-"
  },
  "investment_minimums": {
    "minimum_initial": "1000",
    "minimum_additional": "1000",
    "minimum_redemption": "1000",
    "minimum_balance": 1000
  },
  "data_fetched_at": "2025-11-11T06:37:49.577Z",
  "errors": [
    "No risk metrics available",
    "No category data available",
    "No top holdings data available"
  ]
}